{
  "main": {
    "id": "7b700c63439799ab",
    "type": "split",
    "children": [
      {
        "id": "75b9fc22f534c77d",
        "type": "tabs",
        "children": [
          {
            "id": "08f1faa916b6ddbe",
            "type": "leaf",
            "state": {
              "type": "markdown",
              "state": {
                "file": "Data Structures/Two Pointers.md",
                "mode": "source",
                "source": false
              },
              "icon": "lucide-file",
              "title": "Two Pointers"
            }
          }
        ]
      }
    ],
    "direction": "vertical"
  },
  "left": {
    "id": "85d38aa73d191ce5",
    "type": "split",
    "children": [
      {
        "id": "49aad5692bcbfaa8",
        "type": "tabs",
        "children": [
          {
            "id": "1629ee32f1ae9401",
            "type": "leaf",
            "state": {
              "type": "file-explorer",
              "state": {
                "sortOrder": "alphabetical"
              },
              "icon": "lucide-folder-closed",
              "title": "Files"
            }
          },
          {
            "id": "c5896f45036d0051",
            "type": "leaf",
            "state": {
              "type": "search",
              "state": {
                "query": "sliding ",
                "matchingCase": false,
                "explainSearch": false,
                "collapseAll": false,
                "extraContext": false,
                "sortOrder": "alphabetical"
              },
              "icon": "lucide-search",
              "title": "Search"
            }
          },
          {
            "id": "34e852b5e2795b27",
            "type": "leaf",
            "state": {
              "type": "bookmarks",
              "state": {},
              "icon": "lucide-bookmark",
              "title": "Bookmarks"
            }
          }
        ]
      }
    ],
    "direction": "horizontal",
    "width": 300
  },
  "right": {
    "id": "bdeff81b5824f9dc",
    "type": "split",
    "children": [
      {
        "id": "87008f3930e2bad5",
        "type": "tabs",
        "children": [
          {
            "id": "5645e0858f0ef3e5",
            "type": "leaf",
            "state": {
              "type": "backlink",
              "state": {
                "file": "Data Structures/Pointer.md",
                "collapseAll": false,
                "extraContext": false,
                "sortOrder": "alphabetical",
                "showSearch": false,
                "searchQuery": "",
                "backlinkCollapsed": false,
                "unlinkedCollapsed": true
              },
              "icon": "links-coming-in",
              "title": "Backlinks for Pointer"
            }
          },
          {
            "id": "d852015e5b021d1e",
            "type": "leaf",
            "state": {
              "type": "outgoing-link",
              "state": {
                "file": "Data Structures/Pointer.md",
                "linksCollapsed": false,
                "unlinkedCollapsed": true
              },
              "icon": "links-going-out",
              "title": "Outgoing links from Pointer"
            }
          },
          {
            "id": "fd118ee8174446cb",
            "type": "leaf",
            "state": {
              "type": "tag",
              "state": {
                "sortOrder": "frequency",
                "useHierarchy": true
              },
              "icon": "lucide-tags",
              "title": "Tags"
            }
          },
          {
            "id": "313bdc1dda6eabc9",
            "type": "leaf",
            "state": {
              "type": "outline",
              "state": {
                "file": "Data Structures/Pointer.md"
              },
              "icon": "lucide-list",
              "title": "Outline of Pointer"
            }
          }
        ]
      }
    ],
    "direction": "horizontal",
    "width": 300,
    "collapsed": true
  },
  "left-ribbon": {
    "hiddenItems": {
      "switcher:Open quick switcher": false,
      "graph:Open graph view": false,
      "canvas:Create new canvas": false,
      "daily-notes:Open today's daily note": false,
      "templates:Insert template": false,
      "command-palette:Open command palette": false
    }
  },
  "active": "08f1faa916b6ddbe",
  "lastOpenFiles": [
    "Data Structures/Patterns.md",
    "Data Structures/Sliding Window.md",
    "Data Structures/Slow and Fast Pointers.md",
    "System Design/System design interviews.md",
    "Data Structures/Arrays & Linked List.md",
    "Data Structures/Two Pointers.md",
    "System Design/What is System Design.md",
    "System Design/OAuth 2.0 and OpenID Connect (OIDC).md",
    "System Design/Circuit Breaker.md",
    "desktop.ini",
    "Rate Limiting.md",
    "System Design/Single Sign-On (SSO).md",
    "System Design/Service Discover.md",
    "System Design/Media/oauth2.webp",
    "System Design/Geohasing.md",
    "System Design/Virtual Machines and Containers.md",
    "System Design/Media/Pasted image 20250108183559.jpg",
    "System Design/GraphQL.md",
    "System Design/Long polling, webSockets, Server-Sent Events(SSE).md",
    "System Design/RESTful API.md",
    "System Design/gRPC,tRPC.md",
    "Data Structures/Pointer.md",
    "System Design/API Gateway.md",
    "System Design/Command and Query Responsibility Segregation (CQRS).md",
    "System Design/Event-Driven Architecture (EDA).md",
    "System Design/Monoliths and Microservices.md",
    "System Design/Event Sourcing.md",
    "System Design/Enterprise Service Bus (ESB).md",
    "System Design/Media/event-driven-architecture.webp",
    "System Design/ACID and BASE consistency models.md",
    "System Design/Media/transaction-states.webp",
    "System Design/Media/cap-theorem.webp",
    "Untitled.canvas",
    "Data Structures/System Design/Media/cdn.webp"
  ]
}